eyegrade/__init__.py
eyegrade/__main__.py
eyegrade/app.py
eyegrade/capture.py
eyegrade/detection.py
eyegrade/exams.py
eyegrade/export.py
eyegrade/eyegrade.py
eyegrade/geometry.py
eyegrade/images.py
eyegrade/scoring.py
eyegrade/sessiondb.py
eyegrade/students.py
eyegrade/utils.py
eyegrade/create/__init__.py
eyegrade/create/create.py
eyegrade/create/latex.py
eyegrade/create/parametric.py
eyegrade/create/parser.py
eyegrade/create/questions.py
eyegrade/data/back.svg
eyegrade/data/camera.svg
eyegrade/data/close.svg
eyegrade/data/continue.svg
eyegrade/data/correct.svg
eyegrade/data/discard.svg
eyegrade/data/edit_id.svg
eyegrade/data/exit.svg
eyegrade/data/export.svg
eyegrade/data/eyegrade.ico
eyegrade/data/incorrect.svg
eyegrade/data/logo-base.svg
eyegrade/data/logo.svg
eyegrade/data/manual_detect.svg
eyegrade/data/new.svg
eyegrade/data/new_id.svg
eyegrade/data/not_found.png
eyegrade/data/not_found.svg
eyegrade/data/open.svg
eyegrade/data/open_file.svg
eyegrade/data/search.svg
eyegrade/data/snapshot.svg
eyegrade/data/start.svg
eyegrade/data/stop.svg
eyegrade/data/unanswered.svg
eyegrade/data/locale/es/LC_MESSAGES/eyegrade.mo
eyegrade/data/locale/gl/LC_MESSAGES/eyegrade.mo
eyegrade/data/svm/cross_classifier.dat.gz
eyegrade/data/svm/cross_classifier_metadata.json
eyegrade/data/svm/digit_classifier.dat.gz
eyegrade/data/svm/digit_classifier_metadata.txt
eyegrade/experiments/__init__.py
eyegrade/experiments/extract_crosses.py
eyegrade/experiments/extract_digits.py
eyegrade/ocr/__init__.py
eyegrade/ocr/classifiers.py
eyegrade/ocr/create_classifier.py
eyegrade/ocr/decide_params.py
eyegrade/ocr/evaluation.py
eyegrade/ocr/preprocessing.py
eyegrade/ocr/sample.py
eyegrade/qtgui/__init__.py
eyegrade/qtgui/dialogs.py
eyegrade/qtgui/examsview.py
eyegrade/qtgui/export.py
eyegrade/qtgui/gui.py
eyegrade/qtgui/students.py
eyegrade/qtgui/widgets.py
eyegrade/qtgui/wizards.py
eyegrade/tools/__init__.py
eyegrade/tools/detect_image.py
tests/__init__.py
tests/test_capture.py
eyegrade-0.9.1.dist-info/AUTHORS.TXT
eyegrade-0.9.1.dist-info/COPYING.TXT
eyegrade-0.9.1.dist-info/METADATA
eyegrade-0.9.1.dist-info/WHEEL
eyegrade-0.9.1.dist-info/entry_points.txt
eyegrade-0.9.1.dist-info/top_level.txt
eyegrade-0.9.1.dist-info/RECORD
