Metadata-Version: 2.1
Name: eyegrade
Version: 0.9.1
Summary: "Grade MCQ exams with a webcam"
Home-page: https://www.eyegrade.org/
Author: Jesus Arias Fisteus
Author-email: jfisteus@gmail.com
Classifier: Development Status :: 5 - Production/Stable
Classifier: Environment :: X11 Applications :: Qt
Classifier: Intended Audience :: Education
Classifier: License :: OSI Approved :: GNU General Public License v3 or later (GPLv3+)
Classifier: Natural Language :: Spanish
Classifier: Natural Language :: English
Classifier: Natural Language :: Galician
Classifier: Operating System :: POSIX :: Linux
Classifier: Operating System :: Microsoft :: Windows
Classifier: Programming Language :: Python
Classifier: Programming Language :: Python :: 3
Classifier: Programming Language :: Python :: 3.10
Classifier: Programming Language :: Python :: 3.11
Classifier: Programming Language :: Python :: 3.12
Classifier: Programming Language :: Python :: 3.13
Classifier: Programming Language :: Python :: 3 :: Only
Classifier: Topic :: Education
Requires-Python: >=3.10
License-File: COPYING.TXT
License-File: AUTHORS.TXT
Requires-Dist: opencv-python==4.10.0.84
Requires-Dist: openpyxl==3.0.9
Requires-Dist: PyQt5==5.14.1
Requires-Dist: numpy==2.2.1
Requires-Dist: et_xmlfile==2.0.0
